assert_one_assert_per_pytest/__init__.py
assert_one_assert_per_pytest/__main__.py
assert_one_assert_per_pytest/cli.py
assert_one_assert_per_pytest/py.typed
assert_one_assert_per_pytest/scanner.py
assert_one_assert_per_pytest-20260104040549.dist-info/licenses/LICENSE.txt
assert_one_assert_per_pytest-20260104040549.dist-info/METADATA
assert_one_assert_per_pytest-20260104040549.dist-info/WHEEL
assert_one_assert_per_pytest-20260104040549.dist-info/entry_points.txt
assert_one_assert_per_pytest-20260104040549.dist-info/top_level.txt
assert_one_assert_per_pytest-20260104040549.dist-info/RECORD
