Metadata-Version: 2.4
Name: assert-one-assert-per-pytest
Version: 20260104040549
Summary: CLI tool to assert that each pytest test function contains exactly one assert statement
Author-email: 10U Labs <dev@10ulabs.com>
License-Expression: Apache-2.0
Project-URL: Homepage, https://github.com/10U-Labs-LLC/assert-one-assert-per-pytest
Project-URL: Repository, https://github.com/10U-Labs-LLC/assert-one-assert-per-pytest
Classifier: Development Status :: 4 - Beta
Classifier: Environment :: Console
Classifier: Intended Audience :: Developers
Classifier: Operating System :: OS Independent
Classifier: Programming Language :: Python :: 3
Classifier: Programming Language :: Python :: 3.10
Classifier: Programming Language :: Python :: 3.11
Classifier: Programming Language :: Python :: 3.12
Classifier: Programming Language :: Python :: 3.13
Classifier: Topic :: Software Development :: Quality Assurance
Classifier: Topic :: Software Development :: Testing
Requires-Python: >=3.10
License-File: LICENSE.txt
Dynamic: license-file
